docs/__init__.py
psmanager/__init__.py
psmanager/project_structure_manager.py
tests/__init__.py
tests/test_psmanager.py
ProjectStructureManager-1.0.0.dist-info/LICENSE
ProjectStructureManager-1.0.0.dist-info/METADATA
ProjectStructureManager-1.0.0.dist-info/WHEEL
ProjectStructureManager-1.0.0.dist-info/top_level.txt
ProjectStructureManager-1.0.0.dist-info/RECORD
