Metadata-Version: 2.1
Name: ProjectStructureManager
Version: 1.0.0
Summary: UNKNOWN
Home-page: UNKNOWN
License: UNKNOWN
Platform: UNKNOWN
License-File: LICENSE
